siili_coding_agents/__init__.py
siili_coding_agents/py.typed
siili_coding_agents/agents/__init__.py
siili_coding_agents/agents/base.py
siili_coding_agents/agents/claude/__init__.py
siili_coding_agents/agents/claude/claude_agent.py
siili_coding_agents/agents/claude/to_sdk_message.py
siili_coding_agents/agents/cursor/__init__.py
siili_coding_agents/agents/cursor/cursor_agent.py
siili_coding_agents/agents/cursor/output_parser.py
siili_coding_agents/git/__init__.py
siili_coding_agents/git/changes.py
siili_coding_agents-0.2.1.dist-info/METADATA
siili_coding_agents-0.2.1.dist-info/WHEEL
siili_coding_agents-0.2.1.dist-info/RECORD
