Metadata-Version: 2.4
Name: siili-coding-agents
Version: 0.2.1
Summary: Pre-built coding agents for AI-assisted software development
Project-URL: Homepage, https://github.com/siilisolutions/siili-ai-sdk
Project-URL: Repository, https://github.com/siilisolutions/siili-ai-sdk
Author-email: Siili Solutions Oyj <info@siili.com>
License-Expression: MIT
Keywords: agents,ai,claude,coding,cursor,developer-tools
Classifier: Development Status :: 4 - Beta
Classifier: Intended Audience :: Developers
Classifier: License :: OSI Approved :: MIT License
Classifier: Programming Language :: Python :: 3
Classifier: Programming Language :: Python :: 3.10
Classifier: Programming Language :: Python :: 3.11
Classifier: Programming Language :: Python :: 3.12
Classifier: Topic :: Scientific/Engineering :: Artificial Intelligence
Classifier: Topic :: Software Development
Requires-Python: >=3.10
Requires-Dist: anyio>=4.0.0
Requires-Dist: claude-code-sdk>=0.0.14
Requires-Dist: python-dotenv>=1.0.1
Requires-Dist: siili-ai-sdk>=0.2.0
Requires-Dist: typer>=0.9.0
Provides-Extra: dev
Requires-Dist: ruff; extra == 'dev'
Requires-Dist: ty; extra == 'dev'
